solar_plus_intelbras/__init__.py
solar_plus_intelbras/enums.py
solar_plus_intelbras/solar_plus_intelbras.py
solar_plus_intelbras-0.1.4.dist-info/METADATA
solar_plus_intelbras-0.1.4.dist-info/WHEEL
solar_plus_intelbras-0.1.4.dist-info/RECORD
